{
	"store": {
		"id": 0,
		"name": "Test Store"
	},
    "server": {
        "port": 8088,
		"remoteUrl": "http://174.138.4.153/sposServer/"
    },
    "logFile": "/home/aggalatis/hippoServer.log",
    "database": {
		"host": "localhost",
		"port": "3366",
		"user": "root",
		"pass": "1q2w3e4r",
		"database": "hippos"
	},
	"summaries": {
		"print": false,
		"email": true,
		"recipients": [
			"factorytech.29@gmail.com"
		]
	},
	"receipt": {
		"header": [
			" * ΕΝΑΡΞΗ ΝΟΜΙΜΗΣ ΑΠΟΔΕΙΞΗΣ *",
			"\r\n",
			" Αριθμός Απόδειξης: {receiptNumber}",
			"\r\n",
			" FASHION CLOTHING MON. ΕΠΕ",
			" ΛΙΑΝ ΕΜΠ ΕΙΔΩΝ ΙΜΑΤΙΣΜΟΥ",
			" ΤΣΙΜΙΣΚΗ 36 ΘΕΣΣΑΛΟΝΙΚΗ",
			" ΑΦΜ 801065692 ΔΟΥ Δ ΘΕΣΣΑΛΟΝΙΚΗΣ",
			" __________________________________",
			" Ημερομηνία: {dateTime}",
			" __________________________________",
			" Χειριστής: {userName}",
			" __________________________________",
			" Τμ   Είδος        Τιμή   Αξία  ΦΠΑ",
			" __________________________________"
		],
		"footer": [
			" __________________________________",
			" Σύνολο                {synolo}",
			" Έκπτωση               {discount}",
			" Πληρωτέο              {finalPrice}",
			" Πληρωμή: {typeOfReceipt}",
			"\r\n\r\n",
			" * ΛΗΞΗ ΝΟΜΙΜΗΣ ΑΠΟΔΕΙΞΗΣ *",
			"      * ΕΥΧΑΡΙΣΤΟΥΜΕ *",
			"\r\n",
			" Σήμανση: \r\n"
		],
		"path": "C:\\receipts\\",
		"print": false
			
	}
}